salla_common/__init__.py
salla_common/hooks.py
salla_common/modules.txt
salla_common/patches.txt
salla_common/utils.py
salla_common/config/__init__.py
salla_common/config/desktop.py
salla_common/config/docs.py
salla_common/event/item.py
salla_common/event/item_price.py
salla_common/event/salla_order.py
salla_common/fixtures/custom_field.json
salla_common/public/.gitkeep
salla_common/public/js/item.js
salla_common/public/js/salla_order.js
salla_common/public/js/salla_order_fulfilment.js
salla_common/public/js/salla_shipment_method_mapping.js
salla_common/salla_common/__init__.py
salla_common/salla_common/doctype/__init__.py
salla_common/salla_common/doctype/salla_defaults/__init__.py
salla_common/salla_common/doctype/salla_defaults/salla_defaults.js
salla_common/salla_common/doctype/salla_defaults/salla_defaults.json
salla_common/salla_common/doctype/salla_defaults/salla_defaults.py
salla_common/salla_common/doctype/salla_defaults/test_salla_defaults.py
salla_common/salla_common/doctype/salla_sync_job/__init__.py
salla_common/salla_common/doctype/salla_sync_job/salla_sync_job.js
salla_common/salla_common/doctype/salla_sync_job/salla_sync_job.json
salla_common/salla_common/doctype/salla_sync_job/salla_sync_job.py
salla_common/salla_common/doctype/salla_sync_job/test_salla_sync_job.py
salla_common/templates/__init__.py
salla_common/templates/pages/__init__.py
salla_common-0.0.1.dist-info/WHEEL
salla_common-0.0.1.dist-info/METADATA
salla_common-0.0.1.dist-info/RECORD
