Metadata-Version: 2.4
Name: salla_common
Version: 0.0.1
Summary: App For Salla Comman Features
Author-email: Golive Solutions <info@golive-solutions.com>
Requires-Python: >=3.10
